{
    "unique_id": "2607.08573v1",
    "title": "SHAP-Weighted Cross-Modal Expert Fusion for Emotion and Sentiment Recognition: Evidence and Limits",
    "source_name": "arXiv",
    "source_type": "preprint",
    "url": "https://arxiv.org/abs/2607.08573v1",
    "publication_date": "2026-07-09T15:06:28Z",
    "discovered_date": "2026-07-10T11:39:21.312490Z",
    "authors": [
        {
            "name": "Adis Alihodzic",
            "email": null,
            "affiliation": null,
            "github_username": null,
            "website": null,
            "extra_metadata": {}
        },
        {
            "name": "Selma Skopljakovic Hubljar",
            "email": null,
            "affiliation": null,
            "github_username": null,
            "website": null,
            "extra_metadata": {}
        }
    ],
    "organization": null,
    "summary": "Multimodal emotion and sentiment recognition is commonly addressed by early fusion, which concatenates modalities before classification, or late fusion, which combines independently trained unimodal predictors. Early fusion can be accurate but monolithic, while late fusion is modular but may lose cross-modal interactions. This paper revisits XAI-guided adaptive fusion (\\xgaf), a tree-based mixture of unimodal and cross-modal experts whose sample-level weights are derived from TreeSHAP attribution magnitudes. We focus on the effect of SHAP attribution reduction when experts have unequal feature dimensionalities. In this setting, mean-abs and median-abs reductions can suppress high-dimensional cross-modal experts, whereas sum-abs reduction preserves total attribution mass. On MELD 7-class emotion recognition, sum-abs \\xgaf{} nearly matches early fusion across three face-sequence aggregators; the Transformer variant reaches 0.5983 \\wf{}, compared with 0.6018 for early fusion and 0.4598 for probability-average late fusion. McNemar testing shows no significant difference between sum-abs \\xgaf{} and early fusion on MELD ($p=1.000$), while \\xgaf{} remains significantly better than late fusion ($p<0.0001$). On CMU-MOSEI 3-class sentiment recognition, sum-abs \\xgaf{} reaches 0.6519 \\wf{}, slightly exceeding early fusion (0.6485) and late fusion (0.5696). Ablation studies show that the main gain comes from adding cross-modal experts, especially the trimodal expert, rather than from complex per-sample routing. Diagnostics further show that mean-abs and median-abs weights are nearly uniform, while sum-abs weights concentrate on the trimodal expert. Thus, the main contribution is a transparent empirical analysis of how SHAP reduction, expert dimensionality, and cross-modal expert design affect modular multimodal fusion.",
    "tags": [
        "cs.ai"
    ],
    "categories": [
        "cs.AI"
    ],
    "technologies": [],
    "programming_languages": [],
    "paper_type": null,
    "github_repository": null,
    "documentation_links": [],
    "related_links": [],
    "seller_pitch": null,
    "why_it_matters": null,
    "build_opportunities": [],
    "risks": [],
    "opportunity_score": 0.55,
    "engineering_score": 0.4,
    "scientific_score": 0.85,
    "startup_score": 0.4,
    "confidence_score": 0.59,
    "novelty_score": 0.8,
    "verification_status": {
        "state": "verified",
        "verified_by": "VerificationEngine",
        "verified_at": "2026-07-10T11:39:25.976078",
        "score": 1.0,
        "notes": "Confidence score not yet computed. Assuming early pass. Engine Status: VERIFIED (Score: 100).",
        "is_breakthrough": false,
        "extra_metadata": {
            "report": {
                "passed_checks": [
                    "Required fields exist",
                    "URL format is valid",
                    "Publication date is valid",
                    "Unique ID in current batch",
                    "Non-empty technical summary",
                    "Title is valid and non-empty",
                    "Raw metadata integrity check passed",
                    "No score malformations detected"
                ],
                "failed_checks": [],
                "warnings": [],
                "verification_score": 100.0,
                "status": "VERIFIED"
            }
        }
    },
    "trend_metadata": {
        "velocity": 0.0,
        "sentiment_score": 0.0,
        "interest_level": "low",
        "growth_percentage": null,
        "mentions_count": 0,
        "sources_count": 0,
        "extra_metadata": {}
    },
    "duplicate_of": null,
    "version": "1.0.0+v1",
    "raw_metadata": {
        "arxiv_id": "2607.08573v1",
        "primary_category": "cs.AI",
        "doi": null,
        "updated": "2026-07-09T15:06:28Z",
        "version": "1"
    },
    "raw_content": "Multimodal emotion and sentiment recognition is commonly addressed by early fusion, which concatenates modalities before classification, or late fusion, which combines independently trained unimodal predictors. Early fusion can be accurate but monolithic, while late fusion is modular but may lose cross-modal interactions. This paper revisits XAI-guided adaptive fusion (\\xgaf), a tree-based mixture of unimodal and cross-modal experts whose sample-level weights are derived from TreeSHAP attribution magnitudes. We focus on the effect of SHAP attribution reduction when experts have unequal feature dimensionalities. In this setting, mean-abs and median-abs reductions can suppress high-dimensional cross-modal experts, whereas sum-abs reduction preserves total attribution mass. On MELD 7-class emotion recognition, sum-abs \\xgaf{} nearly matches early fusion across three face-sequence aggregators; the Transformer variant reaches 0.5983 \\wf{}, compared with 0.6018 for early fusion and 0.4598 for probability-average late fusion. McNemar testing shows no significant difference between sum-abs \\xgaf{} and early fusion on MELD ($p=1.000$), while \\xgaf{} remains significantly better than late fusion ($p<0.0001$). On CMU-MOSEI 3-class sentiment recognition, sum-abs \\xgaf{} reaches 0.6519 \\wf{}, slightly exceeding early fusion (0.6485) and late fusion (0.5696). Ablation studies show that the main gain comes from adding cross-modal experts, especially the trimodal expert, rather than from complex per-sample routing. Diagnostics further show that mean-abs and median-abs weights are nearly uniform, while sum-abs weights concentrate on the trimodal expert. Thus, the main contribution is a transparent empirical analysis of how SHAP reduction, expert dimensionality, and cross-modal expert design affect modular multimodal fusion.",
    "signals": [
        "Explore general systems engineering applicability."
    ],
    "is_verified": true,
    "verifier_notes": "Confidence score not yet computed. Assuming early pass. Engine Status: VERIFIED (Score: 100).",
    "collected_at": "2026-07-10T11:39:21.312490+00:00"
}